{"GlobalPropertiesHash":"KMr8Mb23qj6VNqUokdCQ9T/A7SKmqZMmRJHNcBeAgsQ=","FingerprintPatternsHash":"gq3WsqcKBUGTSNle7RKKyXRIwh7M8ccEqOqYvIzoM04=","PropertyOverridesHash":"8ZRc1sGeVrPBx4lD717BgRaQekyh78QKV9SKsdt638U=","InputHashes":["3NT5SarCSlNdYDHfzY6TgGJFciyo0k1uXOCgH6mMT\u002BY=","gvI90ooUEBTZuHIFXYm1Gzd5XonWOUFKE8McmDR5IFw=","HUYS2fzoK0DA8Fb/67d2bIayMnpqhTbYMUOeE/8DFzg=","IihGL/MiI43lCQhKJHNHBAqe46ouLdgwpfIPYoPN9Pc="],"CachedAssets":{"3NT5SarCSlNdYDHfzY6TgGJFciyo0k1uXOCgH6mMT\u002BY=":{"Identity":"C:\\Users\\Monster\\Desktop\\yemeksiparismete\\yemeksiparismete\\yemeksiparismete.Server\\wwwroot\\.gitkeep","SourceId":"yemeksiparismete.Server","SourceType":"Discovered","ContentRoot":"C:\\Users\\Monster\\Desktop\\yemeksiparismete\\yemeksiparismete\\yemeksiparismete.Server\\wwwroot\\","BasePath":"_content/yemeksiparismete.Server","RelativePath":"#[.{fingerprint}]?.gitkeep","AssetKind":"All","AssetMode":"All","AssetRole":"Primary","AssetMergeBehavior":null,"AssetMergeSource":"","RelatedAsset":null,"AssetTraitName":null,"AssetTraitValue":null,"Fingerprint":"wgnqcjo5v7","Integrity":"sI6z2DVhDaKPLXO35dstabR\u002Bg8RltfI135/R5TRgnlA=","CopyToOutputDirectory":"Never","CopyToPublishDirectory":"PreserveNewest","OriginalItemSpec":"wwwroot\\.gitkeep","FileLength":65,"LastWriteTime":"2026-05-08T12:56:08.8967841+00:00"}},"CachedCopyCandidates":{}}